AUTHORS
ChangeLog
Makefile
README.rst
requirements.txt
setup.cfg
setup.py
./rkd_python/__init__.py
./rkd_python/core.py
./rkd_python.egg-info/SOURCES.txt
test/test_standardlib_python_publish.py
test/test_standardlib_unittest.py