Metadata-Version: 2.1
Name: rkd_python
Version: 2.3.3.dev4
Summary: Python-related tasks for RKD, including building, testing and releasing packages
Home-page: https://riotkit-do.readthedocs.io/en/latest/standardlib/python.html
Author: RiotKit non-profit organization
Author-email: riotkit@riseup.net
License: Apache-2
Keywords: rkd,building,continuous-integration,development,devops
Platform: UNKNOWN
Classifier: Development Status :: 4 - Beta
Classifier: Environment :: Console
Classifier: Intended Audience :: Developers
Classifier: Intended Audience :: Information Technology
Classifier: License :: OSI Approved :: Apache Software License
Classifier: Operating System :: OS Independent
Classifier: Programming Language :: Python
